src/taras_mykol_character_counter/__init__.py
src/taras_mykol_character_counter/task3_collections.py
taras_mykol_character_counter-0.1.0.dist-info/METADATA
taras_mykol_character_counter-0.1.0.dist-info/WHEEL
taras_mykol_character_counter-0.1.0.dist-info/licenses/LICENSE
taras_mykol_character_counter-0.1.0.dist-info/RECORD
