Metadata-Version: 2.1
Name: taras_mykol_character_counter
Version: 0.1.0
Summary: a program that counts unique characters
Project-URL: Homepage, https://git.foxminded.ua/foxstudent106344/task-4-cli
Author-email: Taras Makutra <tarik9598@gmail.com>
License-File: LICENSE
Classifier: License :: OSI Approved :: MIT License
Classifier: Operating System :: OS Independent
Classifier: Programming Language :: Python :: 3
Requires-Python: >=3.8
